{
    "total": 36,
    "user_type": "USER",
    "observations": [{
        "observation_id": 1,
        "title": "cultural deviations",
        "reported_date": "11/5/2020 at 12:15 PM",
        "assigned_to": {
            "name": "vamsi",
            "mobile_number": "9550131867",
            "profile_pic":"https://cdn.zeplin.io/5d0afc9102b7fa56760995cc/assets/a2aef3cf-5632-4015-9ea6-4ac3703d9c24@3x.png"
        },
        "severity": "low",
        "status": "CLOSED",
        "due_date": "11/5/2020 at 12:15 PM",
        "category": {
            "name": "Assert Management",
            "category_id": 1
        },
        "sub_category": {
            "name": "Food",
            "sub_category_id": 1
        }
    }, {
        "title": "cultural deviations",
        "observation_id": 2,
        "reported_date": "11/5/2020 at 12:15 PM",
        "severity": "high",
        "status": "CLOSED",
        "due_date": "11/5/2020 at 12:15 PM",
        "category": {
            "name": "Assert Management",
            "category_id": 1
        },
        "sub_category": {
            "name": "Food",
            "sub_category_id": 1
        }
    }, {
        "title": "cultural deviations",
        "observation_id":3,
        "reported_date": "11/5/2020 at 12:15 PM",
        "assigned_to": {
            "name": "vamsi",
            "mobile_number": "9550131867",
            "profile_pic":"https://cdn.zeplin.io/5d0afc9102b7fa56760995cc/assets/a2aef3cf-5632-4015-9ea6-4ac3703d9c24@3x.png"
        },
        "severity": "high",
        "status": "CLOSED",
        "due_date": "11/5/2020 at 12:15 PM",
        "category": {
            "name": "Assert Management",
            "category_id": 1
        },
        "sub_category": {
            "name": "Food",
            "sub_category_id": 1
        }
    }, {
        "title": "cultural deviations",
        "observation_id":4,
        "reported_date": "11/5/2020 at 12:15 PM",
        "assigned_to": {
            "name": "low",
            "mobile_number": "9550131867",
            "profile_pic":"https://cdn.zeplin.io/5d0afc9102b7fa56760995cc/assets/a2aef3cf-5632-4015-9ea6-4ac3703d9c24@3x.png"
        },
        "severity": "high",
        "status": "CLOSED",
        "due_date": "11/5/2020 at 12:15 PM",
        "category": {
            "name": "Assert Management",
            "category_id": 1
        },
        "sub_category": {
            "name": "Food",
            "sub_category_id": 1
        }
    }, {
        "title": "cultural deviations",
        "observation_id":5,
        "reported_date": "11/5/2020 at 12:15 PM",
        "assigned_to": {
            "name": "vamsi",
            "mobile_number": "9550131867",
            "profile_pic":"https://cdn.zeplin.io/5d0afc9102b7fa56760995cc/assets/a2aef3cf-5632-4015-9ea6-4ac3703d9c24@3x.png"
        },
        "severity": "medium",
        "status": "CLOSED",
        "due_date": "11/5/2020 at 12:15 PM",
        "category": {
            "name": "Assert Management",
            "category_id": 1
        },
        "sub_category": {
            "name": "Food",
            "sub_category_id": 1
        }
    }, {
        "title": "cultural deviations",
        "observation_id":6,
        "reported_date": "11/5/2020 at 12:15 PM",
        "assigned_to": {
            "name": "vamsi",
            "mobile_number": "9550131867",
            "profile_pic":"https://cdn.zeplin.io/5d0afc9102b7fa56760995cc/assets/a2aef3cf-5632-4015-9ea6-4ac3703d9c24@3x.png"
        },
        "severity": "high",
        "status": "CLOSED",
        "due_date": "11/5/2020 at 12:15 PM",
        "category": {
            "name": "Assert Management",
            "category_id": 1
        },
        "sub_category": {
            "name": "Food",
            "sub_category_id": 1
        }
    }, {
        "title": "cultural deviations",
        "observation_id":7,
        "reported_date": "11/5/2020 at 12:15 PM",
        "assigned_to": {
            "name": "vamsi",
            "mobile_number": "9550131867",
            "profile_pic":"https://cdn.zeplin.io/5d0afc9102b7fa56760995cc/assets/a2aef3cf-5632-4015-9ea6-4ac3703d9c24@3x.png"
        },
        "severity": "high",
        "status": "CLOSED",
        "due_date": "11/5/2020 at 12:15 PM",
        "category": {
            "name": "Assert Management",
            "category_id": 1
        },
        "sub_category": {
            "name": "Food",
            "sub_category_id": 1
        }
    }, {
        "title": "cultural deviations",
        "observation_id":8,
        "reported_date": "11/5/2020 at 12:15 PM",
        "assigned_to": {
            "name": "vamsi",
            "mobile_number": "9550131867",
            "profile_pic":"https://cdn.zeplin.io/5d0afc9102b7fa56760995cc/assets/a2aef3cf-5632-4015-9ea6-4ac3703d9c24@3x.png"
        },
        "severity": "high",
        "status": "CLOSED",
        "due_date": "11/5/2020 at 12:15 PM",
        "category": {
            "name": "Assert Management",
            "category_id": 1
        },
        "sub_category": {
            "name": "Food",
            "sub_category_id": 1
        }
    }, {
        "title": "cultural deviations",
        "observation_id":9,
        "reported_date": "11/5/2020 at 12:15 PM",
        "assigned_to": {
            "name": "vamsi",
            "mobile_number": "9550131867",
            "profile_pic":"https://cdn.zeplin.io/5d0afc9102b7fa56760995cc/assets/a2aef3cf-5632-4015-9ea6-4ac3703d9c24@3x.png"
        },
        "severity": "high",
        "status": "CLOSED",
        "due_date": "11/5/2020 at 12:15 PM",
        "category": {
            "name": "Assert Management",
            "category_id": 1
        },
        "sub_category": {
            "name": "Food",
            "sub_category_id": 1
        }
    }, {
        "title": "cultural deviations",
        "observation_id":10,
        "reported_date": "11/5/2020 at 12:15 PM",
        "assigned_to": {
            "name": "vamsi",
            "mobile_number": "9550131867",
            "profile_pic":"https://cdn.zeplin.io/5d0afc9102b7fa56760995cc/assets/a2aef3cf-5632-4015-9ea6-4ac3703d9c24@3x.png"
        },
        "severity": "high",
        "status": "CLOSED",
        "due_date": "11/5/2020 at 12:15 PM",
        "category": {
            "name": "Assert Management",
            "category_id": 1
        },
        "sub_category": {
            "name": "Food",
            "sub_category_id": 1
        }
    }, {
        "title": "cultural deviations",
        "observation_id":11,
        "reported_date": "11/5/2020 at 12:15 PM",
        "assigned_to": {
            "name": "vamsi",
            "mobile_number": "9550131867",
            "profile_pic":"https://cdn.zeplin.io/5d0afc9102b7fa56760995cc/assets/a2aef3cf-5632-4015-9ea6-4ac3703d9c24@3x.png"
        },
        "severity": "high",
        "status": "CLOSED",
        "due_date": "11/5/2020 at 12:15 PM",
        "category": {
            "name": "Assert Management",
            "category_id": 1
        },
        "sub_category": {
            "name": "Food",
            "sub_category_id": 1
        }
    }, {
        "title": "cultural deviations",
        "observation_id":12,
        "reported_date": "11/5/2020 at 12:15 PM",
        "assigned_to": {
            "name": "vamsi",
            "mobile_number": "9550131867",
            "profile_pic":"https://cdn.zeplin.io/5d0afc9102b7fa56760995cc/assets/a2aef3cf-5632-4015-9ea6-4ac3703d9c24@3x.png"
        },
        "severity": "high",
        "status": "CLOSED",
        "due_date": "11/5/2020 at 12:15 PM",
        "category": {
            "name": "Assert Management",
            "category_id": 1
        },
        "sub_category": {
            "name": "Food",
            "sub_category_id": 1
        }
    }, {
        "title": "cultural deviations",
        "observation_id":13,
        "reported_date": "11/5/2020 at 12:15 PM",
        "assigned_to": {
            "name": "vamsi",
            "mobile_number": "9550131867",
            "profile_pic":"https://cdn.zeplin.io/5d0afc9102b7fa56760995cc/assets/a2aef3cf-5632-4015-9ea6-4ac3703d9c24@3x.png"
        },
        "severity": "low",
        "status": "CLOSED",
        "due_date": "11/5/2020 at 12:15 PM",
        "category": {
            "name": "Assert Management",
            "category_id": 1
        },
        "sub_category": {
            "name": "Food",
            "sub_category_id": 1
        }
    }, {
        "title": "cultural deviations",
        "observation_id":14,
        "reported_date": "11/5/2020 at 12:15 PM",
        "assigned_to": {
            "name": "vamsi",
            "mobile_number": "9550131867",
            "profile_pic":"https://cdn.zeplin.io/5d0afc9102b7fa56760995cc/assets/a2aef3cf-5632-4015-9ea6-4ac3703d9c24@3x.png"
        },
        "severity": "high",
        "status": "CLOSED",
        "due_date": "11/5/2020 at 12:15 PM",
        "category": {
            "name": "Assert Management",
            "category_id": 1
        },
        "sub_category": {
            "name": "Food",
            "sub_category_id": 1
        }
    }, {
        "title": "cultural deviations",
        "observation_id":15,
        "reported_date": "11/5/2020 at 12:15 PM",
        "assigned_to": {
            "name": "vamsi",
            "mobile_number": "9550131867",
            "profile_pic":"https://cdn.zeplin.io/5d0afc9102b7fa56760995cc/assets/a2aef3cf-5632-4015-9ea6-4ac3703d9c24@3x.png"
        },
        "severity": "high",
        "status": "CLOSED",
        "due_date": "11/5/2020 at 12:15 PM",
        "category": {
            "name": "Assert Management",
            "category_id": 1
        },
        "sub_category": {
            "name": "Food",
            "sub_category_id": 1
        }
    }, {
        "title": "cultural deviations",
        "observation_id":16,
        "reported_date": "11/5/2020 at 12:15 PM",
        "assigned_to": {
            "name": "low",
            "mobile_number": "9550131867",
            "profile_pic":"https://cdn.zeplin.io/5d0afc9102b7fa56760995cc/assets/a2aef3cf-5632-4015-9ea6-4ac3703d9c24@3x.png"
        },
        "severity": "high",
        "status": "CLOSED",
        "due_date": "11/5/2020 at 12:15 PM",
        "category": {
            "name": "Assert Management",
            "category_id": 1
        },
        "sub_category": {
            "name": "Food",
            "sub_category_id": 1
        }
    }, {
        "title": "cultural deviations",
        "observation_id":17,
        "reported_date": "11/5/2020 at 12:15 PM",
        "assigned_to": {
            "name": "vamsi",
            "mobile_number": "9550131867",
            "profile_pic":"https://cdn.zeplin.io/5d0afc9102b7fa56760995cc/assets/a2aef3cf-5632-4015-9ea6-4ac3703d9c24@3x.png"
        },
        "severity": "medium",
        "status": "CLOSED",
        "due_date": "11/5/2020 at 12:15 PM",
        "category": {
            "name": "Assert Management",
            "category_id": 1
        },
        "sub_category": {
            "name": "Food",
            "sub_category_id": 1
        }
    }, {
        "title": "cultural deviations",
        "observation_id":18,
        "reported_date": "11/5/2020 at 12:15 PM",
        "assigned_to": {
            "name": "vamsi",
            "mobile_number": "9550131867",
            "profile_pic":"https://cdn.zeplin.io/5d0afc9102b7fa56760995cc/assets/a2aef3cf-5632-4015-9ea6-4ac3703d9c24@3x.png"
        },
        "severity": "high",
        "status": "CLOSED",
        "due_date": "11/5/2020 at 12:15 PM",
        "category": {
            "name": "Assert Management",
            "category_id": 1
        },
        "sub_category": {
            "name": "Food",
            "sub_category_id": 1
        }
    }, {
        "title": "cultural deviations",
        "observation_id":19,
        "reported_date": "11/5/2020 at 12:15 PM",
        "assigned_to": {
            "name": "vamsi",
            "mobile_number": "9550131867",
            "profile_pic":"https://cdn.zeplin.io/5d0afc9102b7fa56760995cc/assets/a2aef3cf-5632-4015-9ea6-4ac3703d9c24@3x.png"
        },
        "severity": "high",
        "status": "CLOSED",
        "due_date": "11/5/2020 at 12:15 PM",
        "category": {
            "name": "Assert Management",
            "category_id": 1
        },
        "sub_category": {
            "name": "Food",
            "sub_category_id": 1
        }
    }, {
        "title": "cultural deviations",
        "observation_id":20,
        "reported_date": "11/5/2020 at 12:15 PM",
        "assigned_to": {
            "name": "vamsi",
            "mobile_number": "9550131867",
            "profile_pic":"https://cdn.zeplin.io/5d0afc9102b7fa56760995cc/assets/a2aef3cf-5632-4015-9ea6-4ac3703d9c24@3x.png"
        },
        "severity": "high",
        "status": "CLOSED",
        "due_date": "11/5/2020 at 12:15 PM",
        "category": {
            "name": "Assert Management",
            "category_id": 1
        },
        "sub_category": {
            "name": "Food",
            "sub_category_id": 1
        }
    }, {
        "title": "cultural deviations",
        "observation_id":21,
        "reported_date": "11/5/2020 at 12:15 PM",
        "assigned_to": {
            "name": "vamsi",
            "mobile_number": "9550131867",
            "profile_pic":"https://cdn.zeplin.io/5d0afc9102b7fa56760995cc/assets/a2aef3cf-5632-4015-9ea6-4ac3703d9c24@3x.png"
        },
        "severity": "high",
        "status": "CLOSED",
        "due_date": "11/5/2020 at 12:15 PM",
        "category": {
            "name": "Assert Management",
            "category_id": 1
        },
        "sub_category": {
            "name": "Food",
            "sub_category_id": 1
        }
    }, {
        "title": "cultural deviations",
        "observation_id":22,
        "reported_date": "11/5/2020 at 12:15 PM",
        "assigned_to": {
            "name": "vamsi",
            "mobile_number": "9550131867",
            "profile_pic":"https://cdn.zeplin.io/5d0afc9102b7fa56760995cc/assets/a2aef3cf-5632-4015-9ea6-4ac3703d9c24@3x.png"
        },
        "severity": "high",
        "status": "CLOSED",
        "due_date": "11/5/2020 at 12:15 PM",
        "category": {
            "name": "Assert Management",
            "category_id": 1
        },
        "sub_category": {
            "name": "Food",
            "sub_category_id": 1
        }
    }, {
        "title": "cultural deviations",
        "observation_id":23,
        "reported_date": "11/5/2020 at 12:15 PM",
        "assigned_to": {
            "name": "vamsi",
            "mobile_number": "9550131867",
            "profile_pic":"https://cdn.zeplin.io/5d0afc9102b7fa56760995cc/assets/a2aef3cf-5632-4015-9ea6-4ac3703d9c24@3x.png"
        },
        "severity": "high",
        "status": "CLOSED",
        "due_date": "11/5/2020 at 12:15 PM",
        "category": {
            "name": "Assert Management",
            "category_id": 1
        },
        "sub_category": {
            "name": "Food",
            "sub_category_id": 1
        }
    }, {
        "title": "cultural deviations",
        "observation_id":24,
        "reported_date": "11/5/2020 at 12:15 PM",
        "assigned_to": {
            "name": "vamsi",
            "mobile_number": "9550131867",
            "profile_pic":"https://cdn.zeplin.io/5d0afc9102b7fa56760995cc/assets/a2aef3cf-5632-4015-9ea6-4ac3703d9c24@3x.png"
        },
        "severity": "high",
        "status": "CLOSED",
        "due_date": "11/5/2020 at 12:15 PM",
        "category": {
            "name": "Assert Management",
            "category_id": 1
        },
        "sub_category": {
            "name": "Food",
            "sub_category_id": 1
        }
    }, {
        "title": "cultural deviations",
        "observation_id":25,
        "reported_date": "11/5/2020 at 12:15 PM",
        "assigned_to": {
            "name": "vamsi",
            "mobile_number": "9550131867",
            "profile_pic":"https://cdn.zeplin.io/5d0afc9102b7fa56760995cc/assets/a2aef3cf-5632-4015-9ea6-4ac3703d9c24@3x.png"
        },
        "severity": "low",
        "status": "CLOSED",
        "due_date": "11/5/2020 at 12:15 PM",
        "category": {
            "name": "Assert Management",
            "category_id": 1
        },
        "sub_category": {
            "name": "Food",
            "sub_category_id": 1
        }
    }, {
        "title": "cultural deviations",
        "observation_id":26,
        "reported_date": "11/5/2020 at 12:15 PM",
        "assigned_to": {
            "name": "vamsi",
            "mobile_number": "9550131867",
            "profile_pic":"https://cdn.zeplin.io/5d0afc9102b7fa56760995cc/assets/a2aef3cf-5632-4015-9ea6-4ac3703d9c24@3x.png"
        },
        "severity": "high",
        "status": "CLOSED",
        "due_date": "11/5/2020 at 12:15 PM",
        "category": {
            "name": "Assert Management",
            "category_id": 1
        },
        "sub_category": {
            "name": "Food",
            "sub_category_id": 1
        }
    }, {
        "title": "cultural deviations",
        "observation_id":27,
        "reported_date": "11/5/2020 at 12:15 PM",
        "assigned_to": {
            "name": "vamsi",
            "mobile_number": "9550131867",
            "profile_pic":"https://cdn.zeplin.io/5d0afc9102b7fa56760995cc/assets/a2aef3cf-5632-4015-9ea6-4ac3703d9c24@3x.png"
        },
        "severity": "high",
        "status": "CLOSED",
        "due_date": "11/5/2020 at 12:15 PM",
        "category": {
            "name": "Assert Management",
            "category_id": 1
        },
        "sub_category": {
            "name": "Food",
            "sub_category_id": 1
        }
    }, {
        "title": "cultural deviations",
        "observation_id":28,
        "reported_date": "11/5/2020 at 12:15 PM",
        "assigned_to": {
            "name": "low",
            "mobile_number": "9550131867",
            "profile_pic":"https://cdn.zeplin.io/5d0afc9102b7fa56760995cc/assets/a2aef3cf-5632-4015-9ea6-4ac3703d9c24@3x.png"
        },
        "severity": "high",
        "status": "CLOSED",
        "due_date": "11/5/2020 at 12:15 PM",
        "category": {
            "name": "Assert Management",
            "category_id": 1
        },
        "sub_category": {
            "name": "Food",
            "sub_category_id": 1
        }
    }, {
        "title": "cultural deviations",
        "observation_id":29,
        "reported_date": "11/5/2020 at 12:15 PM",
        "assigned_to": {
            "name": "vamsi",
            "mobile_number": "9550131867",
            "profile_pic":"https://cdn.zeplin.io/5d0afc9102b7fa56760995cc/assets/a2aef3cf-5632-4015-9ea6-4ac3703d9c24@3x.png"
        },
        "severity": "medium",
        "status": "CLOSED",
        "due_date": "11/5/2020 at 12:15 PM",
        "category": {
            "name": "Assert Management",
            "category_id": 1
        },
        "sub_category": {
            "name": "Food",
            "sub_category_id": 1
        }
    }, {
        "title": "cultural deviations",
        "observation_id":30,
        "reported_date": "11/5/2020 at 12:15 PM",
        "assigned_to": {
            "name": "vamsi",
            "mobile_number": "9550131867",
            "profile_pic":"https://cdn.zeplin.io/5d0afc9102b7fa56760995cc/assets/a2aef3cf-5632-4015-9ea6-4ac3703d9c24@3x.png"
        },
        "severity": "high",
        "status": "CLOSED",
        "due_date": "11/5/2020 at 12:15 PM",
        "category": {
            "name": "Assert Management",
            "category_id": 1
        },
        "sub_category": {
            "name": "Food",
            "sub_category_id": 1
        }
    }, {
        "title": "cultural deviations",
        "observation_id":31,
        "reported_date": "11/5/2020 at 12:15 PM",
        "assigned_to": {
            "name": "vamsi",
            "mobile_number": "9550131867",
            "profile_pic":"https://cdn.zeplin.io/5d0afc9102b7fa56760995cc/assets/a2aef3cf-5632-4015-9ea6-4ac3703d9c24@3x.png"
        },
        "severity": "high",
        "status": "CLOSED",
        "due_date": "11/5/2020 at 12:15 PM",
        "category": {
            "name": "Assert Management",
            "category_id": 1
        },
        "sub_category": {
            "name": "Food",
            "sub_category_id": 1
        }
    }, {
        "title": "cultural deviations",
        "observation_id":32,
        "reported_date": "11/5/2020 at 12:15 PM",
        "assigned_to": {
            "name": "vamsi",
            "mobile_number": "9550131867",
            "profile_pic":"https://cdn.zeplin.io/5d0afc9102b7fa56760995cc/assets/a2aef3cf-5632-4015-9ea6-4ac3703d9c24@3x.png"
        },
        "severity": "high",
        "status": "CLOSED",
        "due_date": "11/5/2020 at 12:15 PM",
        "category": {
            "name": "Assert Management",
            "category_id": 1
        },
        "sub_category": {
            "name": "Food",
            "sub_category_id": 1
        }
    }, {
        "title": "cultural deviations",
        "observation_id":33,
        "reported_date": "11/5/2020 at 12:15 PM",
        "assigned_to": {
            "name": "vamsi",
            "mobile_number": "9550131867",
            "profile_pic":"https://cdn.zeplin.io/5d0afc9102b7fa56760995cc/assets/a2aef3cf-5632-4015-9ea6-4ac3703d9c24@3x.png"
        },
        "severity": "high",
        "status": "CLOSED",
        "due_date": "11/5/2020 at 12:15 PM",
        "category": {
            "name": "Assert Management",
            "category_id": 1
        },
        "sub_category": {
            "name": "Food",
            "sub_category_id": 1
        }
    }, {
        "title": "cultural deviations",
        "observation_id":34,
        "reported_date": "11/5/2020 at 12:15 PM",
        "assigned_to": {
            "name": "vamsi",
            "mobile_number": "9550131867",
            "profile_pic":"https://cdn.zeplin.io/5d0afc9102b7fa56760995cc/assets/a2aef3cf-5632-4015-9ea6-4ac3703d9c24@3x.png"
        },
        "severity": "high",
        "status": "CLOSED",
        "due_date": "11/5/2020 at 12:15 PM",
        "category": {
            "name": "Assert Management",
            "category_id": 1
        },
        "sub_category": {
            "name": "Food",
            "sub_category_id": 1
        }
    }, {
        "title": "cultural deviations",
        "observation_id":35,
        "reported_date": "11/5/2020 at 12:15 PM",
        "assigned_to": {
            "name": "vamsi",
            "mobile_number": "9550131867",
            "profile_pic":"https://cdn.zeplin.io/5d0afc9102b7fa56760995cc/assets/a2aef3cf-5632-4015-9ea6-4ac3703d9c24@3x.png"
        },
        "severity": "high",
        "status": "CLOSED",
        "due_date": "11/5/2020 at 12:15 PM",
        "category": {
            "name": "Assert Management",
            "category_id": 1
        },
        "sub_category": {
            "name": "Food",
            "sub_category_id": 1
        }
    }, {
        "title": "cultural deviations",
        "observation_id":36,
        "reported_date": "11/5/2020 at 12:15 PM",
        "assigned_to": {
            "name": "vamsi",
            "mobile_number": "9550131867",
            "profile_pic":"https://cdn.zeplin.io/5d0afc9102b7fa56760995cc/assets/a2aef3cf-5632-4015-9ea6-4ac3703d9c24@3x.png"
        },
        "severity": "high",
        "status": "CLOSED",
        "due_date": "11/5/2020 at 12:15 PM",
        "category": {
            "name": "Assert Management",
            "category_id": 1
        },
        "sub_category": {
            "name": "Food",
            "sub_category_id": 1
        }
    }]
}
